oncall_slackbot/__init__.py
oncall_slackbot/bot.py
oncall_slackbot/manager.py
oncall_slackbot/settings.py
oncall_slackbot/slackclient.py
oncall_slackbot/utils.py
oncall_slackbot/integrations/__init__.py
oncall_slackbot/integrations/pagerduty.py
oncall_slackbot/integrations/nlp/__init__.py
oncall_slackbot/integrations/nlp/spacy.py
oncall_slackbot/plugins/__init__.py
oncall_slackbot/plugins/blocks.py
oncall_slackbot/plugins/hello.py
oncall_slackbot/plugins/nlp.py
oncall_slackbot/plugins/oncall.py
oncall_slackbot/plugins/upload.py
oncall_slackbot-1.338.dist-info/LICENSE.txt
oncall_slackbot-1.338.dist-info/METADATA
oncall_slackbot-1.338.dist-info/WHEEL
oncall_slackbot-1.338.dist-info/top_level.txt
oncall_slackbot-1.338.dist-info/RECORD
