Metadata-Version: 2.1
Name: oncall-slackbot
Version: 1.338
Summary: Slackbot made specifically to handle on-call requests
Home-page: http://github.com/bluesliverx/oncall-slackbot
Author: Brian Saville
Author-email: bksaville@gmail.com
License: MIT
Platform: Any
Classifier: Development Status :: 4 - Beta
Classifier: License :: OSI Approved :: MIT License
Classifier: Operating System :: OS Independent
Classifier: Programming Language :: Python
Classifier: Programming Language :: Python :: 3
Classifier: Programming Language :: Python :: 3.4
Classifier: Programming Language :: Python :: 3.5
Classifier: Programming Language :: Python :: 3.6
Classifier: Programming Language :: Python :: 3.7
Requires-Dist: pygerduty >=0.38.2
Requires-Dist: pytz >=2019.3
Requires-Dist: humanize >=3.14.0
Requires-Dist: spacy <3
Requires-Dist: slack-sdk >=3.15.1
